requirements.txt
data/dive_pred_model_v2.pkl
data/substitution_matrix_grantham.tsv
shark_atplab/VERSION
shark_atplab/__init__.py
shark_atplab/settings.py
shark_atplab/core/__init__.py
shark_atplab/core/alf_scoring.py
shark_atplab/core/sequence_pair_similarity.py
shark_atplab/core/utils.py
shark_atplab/dive/__init__.py
shark_atplab/dive/prediction.py
shark_atplab/dive/run.py
tests/__init__.py
tests/core/__init__.py
tests/core/test_alf_scoring.py
tests/core/test_sequence_pair_similarity.py
tests/core/test_utils.py
tests/dive/__init__.py
tests/dive/test_prediction.py
tests/dive/test_run.py
shark_atplab-1.0.1.dist-info/LICENSE
shark_atplab-1.0.1.dist-info/METADATA
shark_atplab-1.0.1.dist-info/WHEEL
shark_atplab-1.0.1.dist-info/top_level.txt
shark_atplab-1.0.1.dist-info/RECORD
