Metadata-Version: 2.1
Name: shark-atplab
Version: 1.0.1
Summary: SHARK-Dive (Similarity/Homology Assessment by Relating K-mers)
Home-page: https://www.biorxiv.org/content/10.1101/2023.06.26.546490v1
Download-URL: https://git.mpi-cbg.de/tothpetroczylab/shark
Author: Willis Chow <chow@mpi-cbg.de>, Soumyadeep Ghosh <soumyadeep11194@gmail.com>, Agnes Toth-Petroczy <tothpet@mpi-cbg.de>, Maxim Scheremetjew <schereme@mpi-cbg.de>
Author-email: chow@mpi-cbg.de
Keywords: Homology Detection,Disordered Proteins,Condensates
Classifier: Development Status :: 4 - Beta
Classifier: Intended Audience :: Science/Research
Classifier: License :: OSI Approved :: BSD License
Classifier: Topic :: Scientific/Engineering :: Bio-Informatics
Classifier: Programming Language :: Python
Classifier: Programming Language :: Python :: 3
Classifier: Programming Language :: Python :: 3 :: Only
Classifier: Programming Language :: Python :: 3.9
Classifier: Programming Language :: Python :: 3.10
Classifier: Programming Language :: Python :: 3.11
Classifier: Operating System :: Unix
Classifier: Operating System :: MacOS
Requires-Python: >=3.6
License-File: LICENSE
Requires-Dist: requests ==2.31.0
Requires-Dist: matplotlib ==3.8.2
Requires-Dist: pandas ==2.1.3
Requires-Dist: catboost ==1.2
Requires-Dist: logomaker ==0.8
Requires-Dist: alfpy ==1.0.6
